<?xml version="1.0" encoding="UTF-8" standalone="no"?><ContractNotice xmlns="urn:oasis:names:specification:ubl:schema:xsd:ContractNotice-2" xmlns:cac="urn:oasis:names:specification:ubl:schema:xsd:CommonAggregateComponents-2" xmlns:cbc="urn:oasis:names:specification:ubl:schema:xsd:CommonBasicComponents-2" xmlns:efac="http://data.europa.eu/p27/eforms-ubl-extension-aggregate-components/1" xmlns:efbc="http://data.europa.eu/p27/eforms-ubl-extension-basic-components/1" xmlns:efext="http://data.europa.eu/p27/eforms-ubl-extensions/1" xmlns:ext="urn:oasis:names:specification:ubl:schema:xsd:CommonExtensionComponents-2" xmlns:xsi="http://www.w3.org/2001/XMLSchema-instance">
   <ext:UBLExtensions>
      <ext:UBLExtension>
         <ext:ExtensionContent>
            <efext:EformsExtension>
               <efac:Changes>
                  <efbc:ChangedNoticeIdentifier>b0547745-621d-4fd3-9c50-26d3416b4ff3-01</efbc:ChangedNoticeIdentifier>
                  <efac:ChangeReason>
                     <cbc:ReasonCode listName="change-corrig-justification">cor-buy</cbc:ReasonCode>
                     <efbc:ReasonDescription languageID="FRA">Report : DLRO au 18/08/2025
Report date limite pour poser des questions au 10/07/2025
Report date limite réponse aux questions au 24/07/2025</efbc:ReasonDescription>
                  </efac:ChangeReason>
               </efac:Changes>
               <efac:NoticeSubType>
                  <cbc:SubTypeCode listName="notice-subtype">16</cbc:SubTypeCode>
               </efac:NoticeSubType>
               <efac:Organizations>
                  <efac:Organization>
                     <efac:Company>
                        <cbc:WebsiteURI>https://www.chu-caen.fr/</cbc:WebsiteURI>
                        <cac:PartyIdentification>
                           <cbc:ID schemeName="organization">ORG-0001</cbc:ID>
                        </cac:PartyIdentification>
                        <cac:PartyName>
                           <cbc:Name languageID="FRA">CHU Caen Normandie</cbc:Name>
                        </cac:PartyName>
                        <cac:PostalAddress>
                           <cbc:StreetName>Cellule marchés publics 
CS 30001</cbc:StreetName>
                           <cbc:CityName>Caen cedex 9</cbc:CityName>
                           <cbc:PostalZone>14033</cbc:PostalZone>
                           <cbc:CountrySubentityCode listName="nuts">FRD11</cbc:CountrySubentityCode>
                           <cac:Country>
                              <cbc:IdentificationCode listName="country">FRA</cbc:IdentificationCode>
                           </cac:Country>
                        </cac:PostalAddress>
                        <cac:PartyLegalEntity>
                           <cbc:CompanyID>26140093100018</cbc:CompanyID>
                        </cac:PartyLegalEntity>
                        <cac:Contact>
                           <cbc:Telephone>0231064885</cbc:Telephone>
                           <cbc:ElectronicMail>rizzottodossin-l@chu-caen.fr</cbc:ElectronicMail>
                        </cac:Contact>
                     </efac:Company>
                  </efac:Organization>
                  <efac:Organization>
                     <efac:Company>
                        <cac:PartyIdentification>
                           <cbc:ID schemeName="organization">ORG-0003</cbc:ID>
                        </cac:PartyIdentification>
                        <cac:PartyName>
                           <cbc:Name languageID="FRA">Comité Consultatif Interdépartemental de Règlement des lites 
CCIRA </cbc:Name>
                        </cac:PartyName>
                        <cac:PostalAddress>
                           <cbc:StreetName>DREETS Pays de Loire
Immeuble Skyline
22 mail Pablo Picasso-BP 24209</cbc:StreetName>
                           <cbc:CityName>NANTES CEDEX 1</cbc:CityName>
                           <cbc:PostalZone>44042</cbc:PostalZone>
                           <cbc:CountrySubentityCode listName="nuts">FRG01</cbc:CountrySubentityCode>
                           <cac:Country>
                              <cbc:IdentificationCode listName="country">FRA</cbc:IdentificationCode>
                           </cac:Country>
                        </cac:PostalAddress>
                        <cac:PartyLegalEntity>
                           <cbc:CompanyID>13002928300012</cbc:CompanyID>
                        </cac:PartyLegalEntity>
                        <cac:Contact>
                           <cbc:Telephone>+33253467902</cbc:Telephone>
                           <cbc:ElectronicMail>paysdl.ccira@direccte.gouv.fr</cbc:ElectronicMail>
                        </cac:Contact>
                     </efac:Company>
                  </efac:Organization>
                  <efac:Organization>
                     <efac:Company>
                        <cac:PartyIdentification>
                           <cbc:ID schemeName="organization">ORG-0002</cbc:ID>
                        </cac:PartyIdentification>
                        <cac:PartyName>
                           <cbc:Name languageID="FRA">Tribunal administratif</cbc:Name>
                        </cac:PartyName>
                        <cac:PostalAddress>
                           <cbc:StreetName>3, rue Arthur le Duc</cbc:StreetName>
                           <cbc:AdditionalStreetName>BP 25086</cbc:AdditionalStreetName>
                           <cbc:CityName>Caen cedex 4</cbc:CityName>
                           <cbc:PostalZone>14050</cbc:PostalZone>
                           <cbc:CountrySubentityCode listName="nuts">FRD11</cbc:CountrySubentityCode>
                           <cac:Country>
                              <cbc:IdentificationCode listName="country">FRA</cbc:IdentificationCode>
                           </cac:Country>
                        </cac:PostalAddress>
                        <cac:PartyLegalEntity>
                           <cbc:CompanyID>17140005400010</cbc:CompanyID>
                        </cac:PartyLegalEntity>
                        <cac:Contact>
                           <cbc:Telephone>+33231707272</cbc:Telephone>
                           <cbc:ElectronicMail>greffe.ta-caen@juradm.fr</cbc:ElectronicMail>
                        </cac:Contact>
                     </efac:Company>
                  </efac:Organization>
               </efac:Organizations>
            <efac:Publication><efbc:NoticePublicationID schemeName="ojs-notice-id">00367152-2025</efbc:NoticePublicationID><efbc:GazetteID schemeName="ojs-id">108/2025</efbc:GazetteID><efbc:PublicationDate>2025-06-06+02:00</efbc:PublicationDate></efac:Publication></efext:EformsExtension>
         </ext:ExtensionContent>
      </ext:UBLExtension>
   </ext:UBLExtensions>
   <cbc:UBLVersionID>2.3</cbc:UBLVersionID>
   <cbc:CustomizationID>eforms-sdk-1.13</cbc:CustomizationID>
   <cbc:ID schemeName="notice-id">8181cdd0-da7c-4bdc-bf26-8f2b6bc05655</cbc:ID>
   <cbc:ContractFolderID>5a46f578-6da8-4824-8853-73587474bbbf</cbc:ContractFolderID>
   <cbc:IssueDate>2025-06-05+02:00</cbc:IssueDate>
   <cbc:IssueTime>11:04:14+02:00</cbc:IssueTime>
   <cbc:VersionID>01</cbc:VersionID>
   <cbc:RegulatoryDomain>32014L0024</cbc:RegulatoryDomain>
   <cbc:NoticeTypeCode listName="competition">cn-standard</cbc:NoticeTypeCode>
   <cbc:NoticeLanguageCode listName="language">FRA</cbc:NoticeLanguageCode>
   <cac:ContractingParty>
      <cbc:BuyerProfileURI>https://www.chu-caen.fr/</cbc:BuyerProfileURI>
      <cac:ContractingPartyType>
         <cbc:PartyTypeCode listName="buyer-legal-type">body-pl</cbc:PartyTypeCode>
      </cac:ContractingPartyType>
      <cac:ContractingActivity>
         <cbc:ActivityTypeCode listName="authority-activity">health</cbc:ActivityTypeCode>
      </cac:ContractingActivity>
      <cac:Party>
         <cac:PartyIdentification>
            <cbc:ID>ORG-0001</cbc:ID>
         </cac:PartyIdentification>
      </cac:Party>
   </cac:ContractingParty>
   <cac:TenderingTerms>
      <cac:TendererQualificationRequest>
         <cac:SpecificTendererRequirement>
            <cbc:TendererRequirementTypeCode listName="exclusion-ground">exg-sitn-other</cbc:TendererRequirementTypeCode>
         </cac:SpecificTendererRequirement>
      </cac:TendererQualificationRequest>
      <cac:TendererQualificationRequest>
         <cac:SpecificTendererRequirement>
            <cbc:TendererRequirementTypeCode listName="exclusion-grounds-source">epo-notice</cbc:TendererRequirementTypeCode>
         </cac:SpecificTendererRequirement>
      </cac:TendererQualificationRequest>
      <cac:LotDistribution>
         <cbc:MaximumLotsAwardedNumeric>5</cbc:MaximumLotsAwardedNumeric>
         <cbc:MaximumLotsSubmittedNumeric>5</cbc:MaximumLotsSubmittedNumeric>
      </cac:LotDistribution>
   </cac:TenderingTerms>
   <cac:TenderingProcess>
      <cbc:ProcedureCode listName="procurement-procedure-type">open</cbc:ProcedureCode>
      <cac:ProcessJustification>
         <cbc:ProcessReasonCode listName="accelerated-procedure">false</cbc:ProcessReasonCode>
      </cac:ProcessJustification>
   </cac:TenderingProcess>
   <cac:ProcurementProject>
      <cbc:ID>GHT2025073</cbc:ID>
      <cbc:Name languageID="FRA">Maintenance préventive et corrective des onduleurs 
et de leurs batteries pour le GHT Normandie Centre</cbc:Name>
      <cbc:Description languageID="FRA">Le marché comprend :
- une maintenance préventive (pièces et consommables, batteries le cas échéant, main d'oeuvre, déplacements et rapports inclus).
- une maintenance corrective à bons de commande avec tarif horaire,  un forfait déplacement et une remise sur catalogue constructeur</cbc:Description>
      <cbc:ProcurementTypeCode listName="contract-nature">services</cbc:ProcurementTypeCode>
      <cac:MainCommodityClassification>
         <cbc:ItemClassificationCode listName="cpv">50532400</cbc:ItemClassificationCode>
      </cac:MainCommodityClassification>
      <cac:RealizedLocation>
         <cbc:Description languageID="FRA">Visite facultative sur site, programmée les 4, 5 et 6 juin 2025, en fonction des établissements concernés (cf. 4.3 du règlement de consultation pour plus de précisions).
Des questions peuvent être posées jusqu'au 10/07/2025, 12h00
Il y sera répondu par le CHU le 24/07/2025, au plus tard.
</cbc:Description>
         <cac:Address>
            <cbc:StreetName>Les prestations s'exécutent dans les 8 établissements concernés par la consultation : voir adresse 1.1 du Règlement de consultation (1 ornais et 7 calvadossiens)</cbc:StreetName>
            <cbc:CityName>Argentan, Aunay Bayeux,  Caen, Falaise, Honfleur, Lisieux, Pont l'Evêque, </cbc:CityName>
            <cbc:PostalZone>14000</cbc:PostalZone>
            <cbc:CountrySubentityCode listName="nuts">FRD11</cbc:CountrySubentityCode>
            <cac:Country>
               <cbc:IdentificationCode listName="country">FRA</cbc:IdentificationCode>
            </cac:Country>
         </cac:Address>
      </cac:RealizedLocation>
   </cac:ProcurementProject>
   <cac:ProcurementProjectLot>
      <cbc:ID schemeName="Lot">LOT-0001</cbc:ID>
      <cac:TenderingTerms>
         <cbc:VariantConstraintCode listName="permission">not-allowed</cbc:VariantConstraintCode>
         <cbc:FundingProgramCode listName="eu-funded">no-eu-funds</cbc:FundingProgramCode>
         <cac:CallForTendersDocumentReference>
            <cbc:ID>https://www.marches-publics.gouv.fr/?page=Entreprise.EntrepriseAdvancedSearch&amp;AllCons&amp;id=2717768&amp;orgAcronyme=x7c</cbc:ID>
            <cbc:DocumentType>non-restricted-document</cbc:DocumentType>
            <cac:Attachment>
               <cac:ExternalReference>
                  <cbc:URI>https://www.marches-publics.gouv.fr/?page=Entreprise.EntrepriseAdvancedSearch&amp;AllCons&amp;id=2717768&amp;orgAcronyme=x7c</cbc:URI>
               </cac:ExternalReference>
            </cac:Attachment>
         </cac:CallForTendersDocumentReference>
         <cac:TendererQualificationRequest>
            <cac:SpecificTendererRequirement>
               <cbc:TendererRequirementTypeCode listName="selection-criteria-source">epo-procurement-document</cbc:TendererRequirementTypeCode>
            </cac:SpecificTendererRequirement>
         </cac:TendererQualificationRequest>
         <cac:TendererQualificationRequest>
            <cac:SpecificTendererRequirement>
               <cbc:TendererRequirementTypeCode listName="reserved-procurement">none</cbc:TendererRequirementTypeCode>
            </cac:SpecificTendererRequirement>
         </cac:TendererQualificationRequest>
         <cac:ContractExecutionRequirement>
            <cbc:ExecutionRequirementCode listName="conditions">performance</cbc:ExecutionRequirementCode>
         </cac:ContractExecutionRequirement>
         <cac:ContractExecutionRequirement>
            <cbc:ExecutionRequirementCode listName="reserved-execution">no</cbc:ExecutionRequirementCode>
         </cac:ContractExecutionRequirement>
         <cac:ContractExecutionRequirement>
            <cbc:ExecutionRequirementCode listName="einvoicing">required</cbc:ExecutionRequirementCode>
         </cac:ContractExecutionRequirement>
         <cac:ContractExecutionRequirement>
            <cbc:ExecutionRequirementCode listName="ecatalog-submission">allowed</cbc:ExecutionRequirementCode>
         </cac:ContractExecutionRequirement>
         <cac:ContractExecutionRequirement>
            <cbc:ExecutionRequirementCode listName="esignature-submission">true</cbc:ExecutionRequirementCode>
         </cac:ContractExecutionRequirement>
         <cac:AwardingTerms>
            <cac:AwardingCriterion>
               <cac:SubordinateAwardingCriterion>
                  <ext:UBLExtensions>
                     <ext:UBLExtension>
                        <ext:ExtensionContent>
                           <efext:EformsExtension>
                              <efac:AwardCriterionParameter>
                                 <efbc:ParameterCode listName="number-weight">per-exa</efbc:ParameterCode>
                                 <efbc:ParameterNumeric>50</efbc:ParameterNumeric>
                              </efac:AwardCriterionParameter>
                           </efext:EformsExtension>
                        </ext:ExtensionContent>
                     </ext:UBLExtension>
                  </ext:UBLExtensions>
                  <cbc:AwardingCriterionTypeCode listName="award-criterion-type">quality</cbc:AwardingCriterionTypeCode>
                  <cbc:Description languageID="FRA">Valeur technique :
- modalités d'organisation des maintenances et mode opératoire: 20 %
- pertinence des moyens humains dédiés à la prestation : 15 % 
- moyens techniques mis à dispositions : 10 % 
-  démarches de sécurité mises en oeuvre : 5 %  
</cbc:Description>
               </cac:SubordinateAwardingCriterion>
               <cac:SubordinateAwardingCriterion>
                  <ext:UBLExtensions>
                     <ext:UBLExtension>
                        <ext:ExtensionContent>
                           <efext:EformsExtension>
                              <efac:AwardCriterionParameter>
                                 <efbc:ParameterCode listName="number-weight">per-exa</efbc:ParameterCode>
                                 <efbc:ParameterNumeric>45</efbc:ParameterNumeric>
                              </efac:AwardCriterionParameter>
                           </efext:EformsExtension>
                        </ext:ExtensionContent>
                     </ext:UBLExtension>
                  </ext:UBLExtensions>
                  <cbc:AwardingCriterionTypeCode listName="award-criterion-type">price</cbc:AwardingCriterionTypeCode>
                  <cbc:Description languageID="FRA">Prix</cbc:Description>
               </cac:SubordinateAwardingCriterion>
               <cac:SubordinateAwardingCriterion>
                  <ext:UBLExtensions>
                     <ext:UBLExtension>
                        <ext:ExtensionContent>
                           <efext:EformsExtension>
                              <efac:AwardCriterionParameter>
                                 <efbc:ParameterCode listName="number-weight">per-exa</efbc:ParameterCode>
                                 <efbc:ParameterNumeric>5</efbc:ParameterNumeric>
                              </efac:AwardCriterionParameter>
                           </efext:EformsExtension>
                        </ext:ExtensionContent>
                     </ext:UBLExtension>
                  </ext:UBLExtensions>
                  <cbc:AwardingCriterionTypeCode listName="award-criterion-type">quality</cbc:AwardingCriterionTypeCode>
                  <cbc:Description languageID="FRA">Démarches environnementales : gestion des déchets : recyclage et traitement des équipements obsolètes et des déchets électroniques</cbc:Description>
               </cac:SubordinateAwardingCriterion>
            </cac:AwardingCriterion>
         </cac:AwardingTerms>
         <cac:AdditionalInformationParty>
            <cac:PartyIdentification>
               <cbc:ID>ORG-0001</cbc:ID>
            </cac:PartyIdentification>
         </cac:AdditionalInformationParty>
         <cac:DocumentProviderParty>
            <cac:PartyIdentification>
               <cbc:ID>ORG-0001</cbc:ID>
            </cac:PartyIdentification>
         </cac:DocumentProviderParty>
         <cac:TenderRecipientParty>
            <cbc:EndpointID>https://www.marches-publics.gouv.fr/?page=Entreprise.EntrepriseAdvancedSearch&amp;AllCons&amp;id=2717768&amp;orgAcronyme=x7c</cbc:EndpointID>
         </cac:TenderRecipientParty>
         <cac:TenderEvaluationParty>
            <cac:PartyIdentification>
               <cbc:ID>ORG-0001</cbc:ID>
            </cac:PartyIdentification>
         </cac:TenderEvaluationParty>
         <cac:TenderValidityPeriod>
            <cbc:DurationMeasure unitCode="DAY">90</cbc:DurationMeasure>
         </cac:TenderValidityPeriod>
         <cac:AppealTerms>
            <cac:AppealInformationParty>
               <cac:PartyIdentification>
                  <cbc:ID>ORG-0002</cbc:ID>
               </cac:PartyIdentification>
            </cac:AppealInformationParty>
            <cac:AppealReceiverParty>
               <cac:PartyIdentification>
                  <cbc:ID>ORG-0002</cbc:ID>
               </cac:PartyIdentification>
            </cac:AppealReceiverParty>
            <cac:MediationParty>
               <cac:PartyIdentification>
                  <cbc:ID>ORG-0003</cbc:ID>
               </cac:PartyIdentification>
            </cac:MediationParty>
         </cac:AppealTerms>
         <cac:Language>
            <cbc:ID>FRA</cbc:ID>
         </cac:Language>
         <cac:PostAwardProcess>
            <cbc:ElectronicOrderUsageIndicator>false</cbc:ElectronicOrderUsageIndicator>
            <cbc:ElectronicPaymentUsageIndicator>true</cbc:ElectronicPaymentUsageIndicator>
         </cac:PostAwardProcess>
      </cac:TenderingTerms>
      <cac:TenderingProcess>
         <cbc:SubmissionMethodCode listName="esubmission">required</cbc:SubmissionMethodCode>
         <cbc:GovernmentAgreementConstraintIndicator>true</cbc:GovernmentAgreementConstraintIndicator>
         <cac:TenderSubmissionDeadlinePeriod>
            <cbc:EndDate>2025-08-18+02:00</cbc:EndDate>
            <cbc:EndTime>12:00:00+02:00</cbc:EndTime>
         </cac:TenderSubmissionDeadlinePeriod>
         <cac:AuctionTerms>
            <cbc:AuctionConstraintIndicator>false</cbc:AuctionConstraintIndicator>
         </cac:AuctionTerms>
         <cac:FrameworkAgreement>
            <cbc:MaximumOperatorQuantity>0</cbc:MaximumOperatorQuantity>
            <cac:SubsequentProcessTenderRequirement>
               <cbc:Name>buyer-categories</cbc:Name>
            </cac:SubsequentProcessTenderRequirement>
         </cac:FrameworkAgreement>
         <cac:ContractingSystem>
            <cbc:ContractingSystemTypeCode listName="framework-agreement">fa-wo-rc</cbc:ContractingSystemTypeCode>
         </cac:ContractingSystem>
         <cac:ContractingSystem>
            <cbc:ContractingSystemTypeCode listName="dps-usage">none</cbc:ContractingSystemTypeCode>
         </cac:ContractingSystem>
      </cac:TenderingProcess>
      <cac:ProcurementProject>
         <cbc:ID>LOT 1</cbc:ID>
         <cbc:Name languageID="FRA">Maintenance des équipements de marque SCHNEIDER et MGE
</cbc:Name>
         <cbc:Description languageID="FRA">Maintenance des équipements de marque SCHNEIDER et MGE
</cbc:Description>
         <cbc:ProcurementTypeCode listName="contract-nature">services</cbc:ProcurementTypeCode>
         <cbc:Note languageID="FRA">S'agissant de la maintenance corrective : accord-cadre sans minimum avec un maximum annuel de 40 000 Euros.
Documents requis : attestation de compétence amiante et d'aptitude médicale des préposés, ou à défaut : moyens mis en oeuvre pour leur obtention.</cbc:Note>
         <cac:MainCommodityClassification>
            <cbc:ItemClassificationCode listName="cpv">50532400</cbc:ItemClassificationCode>
         </cac:MainCommodityClassification>
         <cac:RealizedLocation>
            <cac:Address>
               <cbc:StreetName>Voir inventaire annexé au CCTP et 1.1. règlement de consultation</cbc:StreetName>
               <cbc:CityName>Caen et Aunay-sur-Odon</cbc:CityName>
               <cbc:PostalZone>14000</cbc:PostalZone>
               <cbc:CountrySubentityCode listName="nuts">FRD11</cbc:CountrySubentityCode>
               <cac:Country>
                  <cbc:IdentificationCode listName="country">FRA</cbc:IdentificationCode>
               </cac:Country>
            </cac:Address>
         </cac:RealizedLocation>
         <cac:PlannedPeriod>
            <cbc:StartDate>2025-11-01+02:00</cbc:StartDate>
            <cbc:EndDate>2026-10-31+02:00</cbc:EndDate>
         </cac:PlannedPeriod>
         <cac:ContractExtension>
            <cbc:MaximumNumberNumeric>3</cbc:MaximumNumberNumeric>
         </cac:ContractExtension>
      </cac:ProcurementProject>
   </cac:ProcurementProjectLot>
   <cac:ProcurementProjectLot>
      <cbc:ID schemeName="Lot">LOT-0002</cbc:ID>
      <cac:TenderingTerms>
         <cbc:VariantConstraintCode listName="permission">not-allowed</cbc:VariantConstraintCode>
         <cbc:FundingProgramCode listName="eu-funded">no-eu-funds</cbc:FundingProgramCode>
         <cac:CallForTendersDocumentReference>
            <cbc:ID>https://www.marches-publics.gouv.fr/?page=Entreprise.EntrepriseAdvancedSearch&amp;AllCons&amp;id=2717768&amp;orgAcronyme=x7c</cbc:ID>
            <cbc:DocumentType>non-restricted-document</cbc:DocumentType>
            <cac:Attachment>
               <cac:ExternalReference>
                  <cbc:URI>https://www.marches-publics.gouv.fr/?page=Entreprise.EntrepriseAdvancedSearch&amp;AllCons&amp;id=2717768&amp;orgAcronyme=x7c</cbc:URI>
               </cac:ExternalReference>
            </cac:Attachment>
         </cac:CallForTendersDocumentReference>
         <cac:TendererQualificationRequest>
            <cac:SpecificTendererRequirement>
               <cbc:TendererRequirementTypeCode listName="selection-criteria-source">epo-procurement-document</cbc:TendererRequirementTypeCode>
            </cac:SpecificTendererRequirement>
         </cac:TendererQualificationRequest>
         <cac:TendererQualificationRequest>
            <cac:SpecificTendererRequirement>
               <cbc:TendererRequirementTypeCode listName="reserved-procurement">none</cbc:TendererRequirementTypeCode>
            </cac:SpecificTendererRequirement>
         </cac:TendererQualificationRequest>
         <cac:ContractExecutionRequirement>
            <cbc:ExecutionRequirementCode listName="conditions">performance</cbc:ExecutionRequirementCode>
         </cac:ContractExecutionRequirement>
         <cac:ContractExecutionRequirement>
            <cbc:ExecutionRequirementCode listName="reserved-execution">no</cbc:ExecutionRequirementCode>
         </cac:ContractExecutionRequirement>
         <cac:ContractExecutionRequirement>
            <cbc:ExecutionRequirementCode listName="einvoicing">required</cbc:ExecutionRequirementCode>
         </cac:ContractExecutionRequirement>
         <cac:ContractExecutionRequirement>
            <cbc:ExecutionRequirementCode listName="ecatalog-submission">allowed</cbc:ExecutionRequirementCode>
         </cac:ContractExecutionRequirement>
         <cac:ContractExecutionRequirement>
            <cbc:ExecutionRequirementCode listName="esignature-submission">true</cbc:ExecutionRequirementCode>
         </cac:ContractExecutionRequirement>
         <cac:AwardingTerms>
            <cac:AwardingCriterion>
               <cac:SubordinateAwardingCriterion>
                  <ext:UBLExtensions>
                     <ext:UBLExtension>
                        <ext:ExtensionContent>
                           <efext:EformsExtension>
                              <efac:AwardCriterionParameter>
                                 <efbc:ParameterCode listName="number-weight">per-exa</efbc:ParameterCode>
                                 <efbc:ParameterNumeric>50</efbc:ParameterNumeric>
                              </efac:AwardCriterionParameter>
                           </efext:EformsExtension>
                        </ext:ExtensionContent>
                     </ext:UBLExtension>
                  </ext:UBLExtensions>
                  <cbc:AwardingCriterionTypeCode listName="award-criterion-type">quality</cbc:AwardingCriterionTypeCode>
                  <cbc:Description languageID="FRA">Valeur technique :
- modalités d'organisation des maintenances et mode opératoire: 20 %
- pertinence des moyens humains dédiés à la prestation : 15 % 
- moyens techniques mis à dispositions : 10 % 
-  démarches de sécurité mises en oeuvre : 5 %  
</cbc:Description>
               </cac:SubordinateAwardingCriterion>
               <cac:SubordinateAwardingCriterion>
                  <ext:UBLExtensions>
                     <ext:UBLExtension>
                        <ext:ExtensionContent>
                           <efext:EformsExtension>
                              <efac:AwardCriterionParameter>
                                 <efbc:ParameterCode listName="number-weight">per-exa</efbc:ParameterCode>
                                 <efbc:ParameterNumeric>45</efbc:ParameterNumeric>
                              </efac:AwardCriterionParameter>
                           </efext:EformsExtension>
                        </ext:ExtensionContent>
                     </ext:UBLExtension>
                  </ext:UBLExtensions>
                  <cbc:AwardingCriterionTypeCode listName="award-criterion-type">price</cbc:AwardingCriterionTypeCode>
                  <cbc:Description languageID="FRA">Prix</cbc:Description>
               </cac:SubordinateAwardingCriterion>
               <cac:SubordinateAwardingCriterion>
                  <ext:UBLExtensions>
                     <ext:UBLExtension>
                        <ext:ExtensionContent>
                           <efext:EformsExtension>
                              <efac:AwardCriterionParameter>
                                 <efbc:ParameterCode listName="number-weight">per-exa</efbc:ParameterCode>
                                 <efbc:ParameterNumeric>5</efbc:ParameterNumeric>
                              </efac:AwardCriterionParameter>
                           </efext:EformsExtension>
                        </ext:ExtensionContent>
                     </ext:UBLExtension>
                  </ext:UBLExtensions>
                  <cbc:AwardingCriterionTypeCode listName="award-criterion-type">quality</cbc:AwardingCriterionTypeCode>
                  <cbc:Description languageID="FRA">Démarches environnementales : gestion des déchets : recyclage et traitement des équipements obsolètes et des déchets électroniques</cbc:Description>
               </cac:SubordinateAwardingCriterion>
            </cac:AwardingCriterion>
         </cac:AwardingTerms>
         <cac:AdditionalInformationParty>
            <cac:PartyIdentification>
               <cbc:ID>ORG-0001</cbc:ID>
            </cac:PartyIdentification>
         </cac:AdditionalInformationParty>
         <cac:DocumentProviderParty>
            <cac:PartyIdentification>
               <cbc:ID>ORG-0001</cbc:ID>
            </cac:PartyIdentification>
         </cac:DocumentProviderParty>
         <cac:TenderRecipientParty>
            <cbc:EndpointID>https://www.marches-publics.gouv.fr/?page=Entreprise.EntrepriseAdvancedSearch&amp;AllCons&amp;id=2717768&amp;orgAcronyme=x7c</cbc:EndpointID>
         </cac:TenderRecipientParty>
         <cac:TenderEvaluationParty>
            <cac:PartyIdentification>
               <cbc:ID>ORG-0001</cbc:ID>
            </cac:PartyIdentification>
         </cac:TenderEvaluationParty>
         <cac:TenderValidityPeriod>
            <cbc:DurationMeasure unitCode="DAY">90</cbc:DurationMeasure>
         </cac:TenderValidityPeriod>
         <cac:AppealTerms>
            <cac:AppealInformationParty>
               <cac:PartyIdentification>
                  <cbc:ID>ORG-0002</cbc:ID>
               </cac:PartyIdentification>
            </cac:AppealInformationParty>
            <cac:AppealReceiverParty>
               <cac:PartyIdentification>
                  <cbc:ID>ORG-0002</cbc:ID>
               </cac:PartyIdentification>
            </cac:AppealReceiverParty>
            <cac:MediationParty>
               <cac:PartyIdentification>
                  <cbc:ID>ORG-0003</cbc:ID>
               </cac:PartyIdentification>
            </cac:MediationParty>
         </cac:AppealTerms>
         <cac:Language>
            <cbc:ID>FRA</cbc:ID>
         </cac:Language>
         <cac:PostAwardProcess>
            <cbc:ElectronicOrderUsageIndicator>false</cbc:ElectronicOrderUsageIndicator>
            <cbc:ElectronicPaymentUsageIndicator>true</cbc:ElectronicPaymentUsageIndicator>
         </cac:PostAwardProcess>
      </cac:TenderingTerms>
      <cac:TenderingProcess>
         <cbc:SubmissionMethodCode listName="esubmission">required</cbc:SubmissionMethodCode>
         <cbc:GovernmentAgreementConstraintIndicator>true</cbc:GovernmentAgreementConstraintIndicator>
         <cac:TenderSubmissionDeadlinePeriod>
            <cbc:EndDate>2025-08-18+02:00</cbc:EndDate>
            <cbc:EndTime>12:00:00+02:00</cbc:EndTime>
         </cac:TenderSubmissionDeadlinePeriod>
         <cac:AuctionTerms>
            <cbc:AuctionConstraintIndicator>false</cbc:AuctionConstraintIndicator>
         </cac:AuctionTerms>
         <cac:FrameworkAgreement>
            <cbc:MaximumOperatorQuantity>0</cbc:MaximumOperatorQuantity>
            <cac:SubsequentProcessTenderRequirement>
               <cbc:Name>buyer-categories</cbc:Name>
            </cac:SubsequentProcessTenderRequirement>
         </cac:FrameworkAgreement>
         <cac:ContractingSystem>
            <cbc:ContractingSystemTypeCode listName="framework-agreement">fa-wo-rc</cbc:ContractingSystemTypeCode>
         </cac:ContractingSystem>
         <cac:ContractingSystem>
            <cbc:ContractingSystemTypeCode listName="dps-usage">none</cbc:ContractingSystemTypeCode>
         </cac:ContractingSystem>
      </cac:TenderingProcess>
      <cac:ProcurementProject>
         <cbc:ID>LOT 2</cbc:ID>
         <cbc:Name languageID="FRA">Maintenance des équipements de marque SOCOMEC
</cbc:Name>
         <cbc:Description languageID="FRA">Maintenance des équipements de marque SOCOMEC</cbc:Description>
         <cbc:ProcurementTypeCode listName="contract-nature">services</cbc:ProcurementTypeCode>
         <cbc:Note languageID="FRA">S'agissant de la maintenance corrective : accord-cadre sans minimum avec un maximum annuel de 20 000 Euros</cbc:Note>
         <cac:MainCommodityClassification>
            <cbc:ItemClassificationCode listName="cpv">50532400</cbc:ItemClassificationCode>
         </cac:MainCommodityClassification>
         <cac:RealizedLocation>
            <cac:Address>
               <cbc:StreetName>Voir inventaire annexé au CCTP et 1.1. règlement de consultation</cbc:StreetName>
               <cbc:CityName>Argentan, Caen, Bayeux</cbc:CityName>
               <cbc:PostalZone>14000
14400
61200</cbc:PostalZone>
               <cbc:CountrySubentityCode listName="nuts">FRD11</cbc:CountrySubentityCode>
               <cac:Country>
                  <cbc:IdentificationCode listName="country">FRA</cbc:IdentificationCode>
               </cac:Country>
            </cac:Address>
         </cac:RealizedLocation>
         <cac:PlannedPeriod>
            <cbc:StartDate>2025-11-01+02:00</cbc:StartDate>
            <cbc:EndDate>2026-10-31+02:00</cbc:EndDate>
         </cac:PlannedPeriod>
         <cac:ContractExtension>
            <cbc:MaximumNumberNumeric>3</cbc:MaximumNumberNumeric>
         </cac:ContractExtension>
      </cac:ProcurementProject>
   </cac:ProcurementProjectLot>
   <cac:ProcurementProjectLot>
      <cbc:ID schemeName="Lot">LOT-0004</cbc:ID>
      <cac:TenderingTerms>
         <cbc:VariantConstraintCode listName="permission">not-allowed</cbc:VariantConstraintCode>
         <cbc:FundingProgramCode listName="eu-funded">no-eu-funds</cbc:FundingProgramCode>
         <cac:CallForTendersDocumentReference>
            <cbc:ID>https://www.marches-publics.gouv.fr/?page=Entreprise.EntrepriseAdvancedSearch&amp;AllCons&amp;id=2717768&amp;orgAcronyme=x7c</cbc:ID>
            <cbc:DocumentType>non-restricted-document</cbc:DocumentType>
            <cac:Attachment>
               <cac:ExternalReference>
                  <cbc:URI>https://www.marches-publics.gouv.fr/?page=Entreprise.EntrepriseAdvancedSearch&amp;AllCons&amp;id=2717768&amp;orgAcronyme=x7c</cbc:URI>
               </cac:ExternalReference>
            </cac:Attachment>
         </cac:CallForTendersDocumentReference>
         <cac:TendererQualificationRequest>
            <cac:SpecificTendererRequirement>
               <cbc:TendererRequirementTypeCode listName="selection-criteria-source">epo-procurement-document</cbc:TendererRequirementTypeCode>
            </cac:SpecificTendererRequirement>
         </cac:TendererQualificationRequest>
         <cac:TendererQualificationRequest>
            <cac:SpecificTendererRequirement>
               <cbc:TendererRequirementTypeCode listName="reserved-procurement">none</cbc:TendererRequirementTypeCode>
            </cac:SpecificTendererRequirement>
         </cac:TendererQualificationRequest>
         <cac:ContractExecutionRequirement>
            <cbc:ExecutionRequirementCode listName="conditions">performance</cbc:ExecutionRequirementCode>
         </cac:ContractExecutionRequirement>
         <cac:ContractExecutionRequirement>
            <cbc:ExecutionRequirementCode listName="reserved-execution">no</cbc:ExecutionRequirementCode>
         </cac:ContractExecutionRequirement>
         <cac:ContractExecutionRequirement>
            <cbc:ExecutionRequirementCode listName="einvoicing">required</cbc:ExecutionRequirementCode>
         </cac:ContractExecutionRequirement>
         <cac:ContractExecutionRequirement>
            <cbc:ExecutionRequirementCode listName="ecatalog-submission">allowed</cbc:ExecutionRequirementCode>
         </cac:ContractExecutionRequirement>
         <cac:ContractExecutionRequirement>
            <cbc:ExecutionRequirementCode listName="esignature-submission">true</cbc:ExecutionRequirementCode>
         </cac:ContractExecutionRequirement>
         <cac:AwardingTerms>
            <cac:AwardingCriterion>
               <cac:SubordinateAwardingCriterion>
                  <ext:UBLExtensions>
                     <ext:UBLExtension>
                        <ext:ExtensionContent>
                           <efext:EformsExtension>
                              <efac:AwardCriterionParameter>
                                 <efbc:ParameterCode listName="number-weight">per-exa</efbc:ParameterCode>
                                 <efbc:ParameterNumeric>50</efbc:ParameterNumeric>
                              </efac:AwardCriterionParameter>
                           </efext:EformsExtension>
                        </ext:ExtensionContent>
                     </ext:UBLExtension>
                  </ext:UBLExtensions>
                  <cbc:AwardingCriterionTypeCode listName="award-criterion-type">quality</cbc:AwardingCriterionTypeCode>
                  <cbc:Description languageID="FRA">Valeur technique :
- modalités d'organisation des maintenances et mode opératoire: 20 %
- pertinence des moyens humains dédiés à la prestation : 15 % 
- moyens techniques mis à dispositions : 10 % 
-  démarches de sécurité mises en oeuvre : 5 %  
</cbc:Description>
               </cac:SubordinateAwardingCriterion>
               <cac:SubordinateAwardingCriterion>
                  <ext:UBLExtensions>
                     <ext:UBLExtension>
                        <ext:ExtensionContent>
                           <efext:EformsExtension>
                              <efac:AwardCriterionParameter>
                                 <efbc:ParameterCode listName="number-weight">per-exa</efbc:ParameterCode>
                                 <efbc:ParameterNumeric>45</efbc:ParameterNumeric>
                              </efac:AwardCriterionParameter>
                           </efext:EformsExtension>
                        </ext:ExtensionContent>
                     </ext:UBLExtension>
                  </ext:UBLExtensions>
                  <cbc:AwardingCriterionTypeCode listName="award-criterion-type">price</cbc:AwardingCriterionTypeCode>
                  <cbc:Description languageID="FRA">Prix</cbc:Description>
               </cac:SubordinateAwardingCriterion>
               <cac:SubordinateAwardingCriterion>
                  <ext:UBLExtensions>
                     <ext:UBLExtension>
                        <ext:ExtensionContent>
                           <efext:EformsExtension>
                              <efac:AwardCriterionParameter>
                                 <efbc:ParameterCode listName="number-weight">per-exa</efbc:ParameterCode>
                                 <efbc:ParameterNumeric>5</efbc:ParameterNumeric>
                              </efac:AwardCriterionParameter>
                           </efext:EformsExtension>
                        </ext:ExtensionContent>
                     </ext:UBLExtension>
                  </ext:UBLExtensions>
                  <cbc:AwardingCriterionTypeCode listName="award-criterion-type">quality</cbc:AwardingCriterionTypeCode>
                  <cbc:Description languageID="FRA">Démarches environnementales : gestion des déchets : recyclage et traitement des équipements obsolètes et des déchets électroniques</cbc:Description>
               </cac:SubordinateAwardingCriterion>
            </cac:AwardingCriterion>
         </cac:AwardingTerms>
         <cac:AdditionalInformationParty>
            <cac:PartyIdentification>
               <cbc:ID>ORG-0001</cbc:ID>
            </cac:PartyIdentification>
         </cac:AdditionalInformationParty>
         <cac:DocumentProviderParty>
            <cac:PartyIdentification>
               <cbc:ID>ORG-0001</cbc:ID>
            </cac:PartyIdentification>
         </cac:DocumentProviderParty>
         <cac:TenderRecipientParty>
            <cbc:EndpointID>https://www.marches-publics.gouv.fr/?page=Entreprise.EntrepriseAdvancedSearch&amp;AllCons&amp;id=2717768&amp;orgAcronyme=x7c</cbc:EndpointID>
         </cac:TenderRecipientParty>
         <cac:TenderEvaluationParty>
            <cac:PartyIdentification>
               <cbc:ID>ORG-0001</cbc:ID>
            </cac:PartyIdentification>
         </cac:TenderEvaluationParty>
         <cac:TenderValidityPeriod>
            <cbc:DurationMeasure unitCode="DAY">90</cbc:DurationMeasure>
         </cac:TenderValidityPeriod>
         <cac:AppealTerms>
            <cac:AppealInformationParty>
               <cac:PartyIdentification>
                  <cbc:ID>ORG-0002</cbc:ID>
               </cac:PartyIdentification>
            </cac:AppealInformationParty>
            <cac:AppealReceiverParty>
               <cac:PartyIdentification>
                  <cbc:ID>ORG-0002</cbc:ID>
               </cac:PartyIdentification>
            </cac:AppealReceiverParty>
            <cac:MediationParty>
               <cac:PartyIdentification>
                  <cbc:ID>ORG-0003</cbc:ID>
               </cac:PartyIdentification>
            </cac:MediationParty>
         </cac:AppealTerms>
         <cac:Language>
            <cbc:ID>FRA</cbc:ID>
         </cac:Language>
         <cac:PostAwardProcess>
            <cbc:ElectronicOrderUsageIndicator>false</cbc:ElectronicOrderUsageIndicator>
            <cbc:ElectronicPaymentUsageIndicator>true</cbc:ElectronicPaymentUsageIndicator>
         </cac:PostAwardProcess>
      </cac:TenderingTerms>
      <cac:TenderingProcess>
         <cbc:SubmissionMethodCode listName="esubmission">required</cbc:SubmissionMethodCode>
         <cbc:GovernmentAgreementConstraintIndicator>true</cbc:GovernmentAgreementConstraintIndicator>
         <cac:TenderSubmissionDeadlinePeriod>
            <cbc:EndDate>2025-08-18+02:00</cbc:EndDate>
            <cbc:EndTime>12:00:00+02:00</cbc:EndTime>
         </cac:TenderSubmissionDeadlinePeriod>
         <cac:AuctionTerms>
            <cbc:AuctionConstraintIndicator>false</cbc:AuctionConstraintIndicator>
         </cac:AuctionTerms>
         <cac:FrameworkAgreement>
            <cbc:MaximumOperatorQuantity>0</cbc:MaximumOperatorQuantity>
            <cac:SubsequentProcessTenderRequirement>
               <cbc:Name>buyer-categories</cbc:Name>
            </cac:SubsequentProcessTenderRequirement>
         </cac:FrameworkAgreement>
         <cac:ContractingSystem>
            <cbc:ContractingSystemTypeCode listName="framework-agreement">fa-wo-rc</cbc:ContractingSystemTypeCode>
         </cac:ContractingSystem>
         <cac:ContractingSystem>
            <cbc:ContractingSystemTypeCode listName="dps-usage">none</cbc:ContractingSystemTypeCode>
         </cac:ContractingSystem>
      </cac:TenderingProcess>
      <cac:ProcurementProject>
         <cbc:ID>LOT 3</cbc:ID>
         <cbc:Name languageID="FRA">Maintenance des équipements de marque EATON
</cbc:Name>
         <cbc:Description languageID="FRA">Maintenance des équipements de marque EATON</cbc:Description>
         <cbc:ProcurementTypeCode listName="contract-nature">services</cbc:ProcurementTypeCode>
         <cbc:Note languageID="FRA">S'agissant de la maintenance corrective : accord-cadre sans minimum avec un maximum annuel de 25 000 Euros</cbc:Note>
         <cac:MainCommodityClassification>
            <cbc:ItemClassificationCode listName="cpv">50532400</cbc:ItemClassificationCode>
         </cac:MainCommodityClassification>
         <cac:RealizedLocation>
            <cac:Address>
               <cbc:StreetName>Voir inventaire annexé au CCTP et 1.1. règlement de consultation</cbc:StreetName>
               <cbc:CityName>Argentan, Caen, Cricqueboeuf, Equemauville</cbc:CityName>
               <cbc:PostalZone>14000
14600
61200</cbc:PostalZone>
               <cbc:CountrySubentityCode listName="nuts">FRD11</cbc:CountrySubentityCode>
               <cac:Country>
                  <cbc:IdentificationCode listName="country">FRA</cbc:IdentificationCode>
               </cac:Country>
            </cac:Address>
         </cac:RealizedLocation>
         <cac:PlannedPeriod>
            <cbc:StartDate>2025-11-01+02:00</cbc:StartDate>
            <cbc:EndDate>2026-10-31+02:00</cbc:EndDate>
         </cac:PlannedPeriod>
         <cac:ContractExtension>
            <cbc:MaximumNumberNumeric>3</cbc:MaximumNumberNumeric>
         </cac:ContractExtension>
      </cac:ProcurementProject>
   </cac:ProcurementProjectLot>
   <cac:ProcurementProjectLot>
      <cbc:ID schemeName="Lot">LOT-0005</cbc:ID>
      <cac:TenderingTerms>
         <cbc:VariantConstraintCode listName="permission">not-allowed</cbc:VariantConstraintCode>
         <cbc:FundingProgramCode listName="eu-funded">no-eu-funds</cbc:FundingProgramCode>
         <cac:CallForTendersDocumentReference>
            <cbc:ID>https://www.marches-publics.gouv.fr/?page=Entreprise.EntrepriseAdvancedSearch&amp;AllCons&amp;id=2717768&amp;orgAcronyme=x7c</cbc:ID>
            <cbc:DocumentType>non-restricted-document</cbc:DocumentType>
            <cac:Attachment>
               <cac:ExternalReference>
                  <cbc:URI>https://www.marches-publics.gouv.fr/?page=Entreprise.EntrepriseAdvancedSearch&amp;AllCons&amp;id=2717768&amp;orgAcronyme=x7c</cbc:URI>
               </cac:ExternalReference>
            </cac:Attachment>
         </cac:CallForTendersDocumentReference>
         <cac:TendererQualificationRequest>
            <cac:SpecificTendererRequirement>
               <cbc:TendererRequirementTypeCode listName="selection-criteria-source">epo-procurement-document</cbc:TendererRequirementTypeCode>
            </cac:SpecificTendererRequirement>
         </cac:TendererQualificationRequest>
         <cac:TendererQualificationRequest>
            <cac:SpecificTendererRequirement>
               <cbc:TendererRequirementTypeCode listName="reserved-procurement">none</cbc:TendererRequirementTypeCode>
            </cac:SpecificTendererRequirement>
         </cac:TendererQualificationRequest>
         <cac:ContractExecutionRequirement>
            <cbc:ExecutionRequirementCode listName="conditions">performance</cbc:ExecutionRequirementCode>
         </cac:ContractExecutionRequirement>
         <cac:ContractExecutionRequirement>
            <cbc:ExecutionRequirementCode listName="reserved-execution">no</cbc:ExecutionRequirementCode>
         </cac:ContractExecutionRequirement>
         <cac:ContractExecutionRequirement>
            <cbc:ExecutionRequirementCode listName="einvoicing">required</cbc:ExecutionRequirementCode>
         </cac:ContractExecutionRequirement>
         <cac:ContractExecutionRequirement>
            <cbc:ExecutionRequirementCode listName="ecatalog-submission">allowed</cbc:ExecutionRequirementCode>
         </cac:ContractExecutionRequirement>
         <cac:ContractExecutionRequirement>
            <cbc:ExecutionRequirementCode listName="esignature-submission">true</cbc:ExecutionRequirementCode>
         </cac:ContractExecutionRequirement>
         <cac:AwardingTerms>
            <cac:AwardingCriterion>
               <cac:SubordinateAwardingCriterion>
                  <ext:UBLExtensions>
                     <ext:UBLExtension>
                        <ext:ExtensionContent>
                           <efext:EformsExtension>
                              <efac:AwardCriterionParameter>
                                 <efbc:ParameterCode listName="number-weight">per-exa</efbc:ParameterCode>
                                 <efbc:ParameterNumeric>50</efbc:ParameterNumeric>
                              </efac:AwardCriterionParameter>
                           </efext:EformsExtension>
                        </ext:ExtensionContent>
                     </ext:UBLExtension>
                  </ext:UBLExtensions>
                  <cbc:AwardingCriterionTypeCode listName="award-criterion-type">quality</cbc:AwardingCriterionTypeCode>
                  <cbc:Description languageID="FRA">Valeur technique :
- modalités d'organisation des maintenances et mode opératoire: 20 %
- pertinence des moyens humains dédiés à la prestation : 15 % 
- moyens techniques mis à dispositions : 10 % 
-  démarches de sécurité mises en oeuvre : 5 %  
</cbc:Description>
               </cac:SubordinateAwardingCriterion>
               <cac:SubordinateAwardingCriterion>
                  <ext:UBLExtensions>
                     <ext:UBLExtension>
                        <ext:ExtensionContent>
                           <efext:EformsExtension>
                              <efac:AwardCriterionParameter>
                                 <efbc:ParameterCode listName="number-weight">per-exa</efbc:ParameterCode>
                                 <efbc:ParameterNumeric>45</efbc:ParameterNumeric>
                              </efac:AwardCriterionParameter>
                           </efext:EformsExtension>
                        </ext:ExtensionContent>
                     </ext:UBLExtension>
                  </ext:UBLExtensions>
                  <cbc:AwardingCriterionTypeCode listName="award-criterion-type">price</cbc:AwardingCriterionTypeCode>
                  <cbc:Description languageID="FRA">Prix</cbc:Description>
               </cac:SubordinateAwardingCriterion>
               <cac:SubordinateAwardingCriterion>
                  <ext:UBLExtensions>
                     <ext:UBLExtension>
                        <ext:ExtensionContent>
                           <efext:EformsExtension>
                              <efac:AwardCriterionParameter>
                                 <efbc:ParameterCode listName="number-weight">per-exa</efbc:ParameterCode>
                                 <efbc:ParameterNumeric>5</efbc:ParameterNumeric>
                              </efac:AwardCriterionParameter>
                           </efext:EformsExtension>
                        </ext:ExtensionContent>
                     </ext:UBLExtension>
                  </ext:UBLExtensions>
                  <cbc:AwardingCriterionTypeCode listName="award-criterion-type">quality</cbc:AwardingCriterionTypeCode>
                  <cbc:Description languageID="FRA">Démarches environnementales : gestion des déchets : recyclage et traitement des équipements obsolètes et des déchets électroniques</cbc:Description>
               </cac:SubordinateAwardingCriterion>
            </cac:AwardingCriterion>
         </cac:AwardingTerms>
         <cac:AdditionalInformationParty>
            <cac:PartyIdentification>
               <cbc:ID>ORG-0001</cbc:ID>
            </cac:PartyIdentification>
         </cac:AdditionalInformationParty>
         <cac:DocumentProviderParty>
            <cac:PartyIdentification>
               <cbc:ID>ORG-0001</cbc:ID>
            </cac:PartyIdentification>
         </cac:DocumentProviderParty>
         <cac:TenderRecipientParty>
            <cbc:EndpointID>https://www.marches-publics.gouv.fr/?page=Entreprise.EntrepriseAdvancedSearch&amp;AllCons&amp;id=2717768&amp;orgAcronyme=x7c</cbc:EndpointID>
         </cac:TenderRecipientParty>
         <cac:TenderEvaluationParty>
            <cac:PartyIdentification>
               <cbc:ID>ORG-0001</cbc:ID>
            </cac:PartyIdentification>
         </cac:TenderEvaluationParty>
         <cac:TenderValidityPeriod>
            <cbc:DurationMeasure unitCode="DAY">90</cbc:DurationMeasure>
         </cac:TenderValidityPeriod>
         <cac:AppealTerms>
            <cac:AppealInformationParty>
               <cac:PartyIdentification>
                  <cbc:ID>ORG-0002</cbc:ID>
               </cac:PartyIdentification>
            </cac:AppealInformationParty>
            <cac:AppealReceiverParty>
               <cac:PartyIdentification>
                  <cbc:ID>ORG-0002</cbc:ID>
               </cac:PartyIdentification>
            </cac:AppealReceiverParty>
            <cac:MediationParty>
               <cac:PartyIdentification>
                  <cbc:ID>ORG-0003</cbc:ID>
               </cac:PartyIdentification>
            </cac:MediationParty>
         </cac:AppealTerms>
         <cac:Language>
            <cbc:ID>FRA</cbc:ID>
         </cac:Language>
         <cac:PostAwardProcess>
            <cbc:ElectronicOrderUsageIndicator>false</cbc:ElectronicOrderUsageIndicator>
            <cbc:ElectronicPaymentUsageIndicator>true</cbc:ElectronicPaymentUsageIndicator>
         </cac:PostAwardProcess>
      </cac:TenderingTerms>
      <cac:TenderingProcess>
         <cbc:SubmissionMethodCode listName="esubmission">required</cbc:SubmissionMethodCode>
         <cbc:GovernmentAgreementConstraintIndicator>true</cbc:GovernmentAgreementConstraintIndicator>
         <cac:TenderSubmissionDeadlinePeriod>
            <cbc:EndDate>2025-08-18+02:00</cbc:EndDate>
            <cbc:EndTime>12:00:00+02:00</cbc:EndTime>
         </cac:TenderSubmissionDeadlinePeriod>
         <cac:AuctionTerms>
            <cbc:AuctionConstraintIndicator>false</cbc:AuctionConstraintIndicator>
         </cac:AuctionTerms>
         <cac:FrameworkAgreement>
            <cbc:MaximumOperatorQuantity>0</cbc:MaximumOperatorQuantity>
            <cac:SubsequentProcessTenderRequirement>
               <cbc:Name>buyer-categories</cbc:Name>
            </cac:SubsequentProcessTenderRequirement>
         </cac:FrameworkAgreement>
         <cac:ContractingSystem>
            <cbc:ContractingSystemTypeCode listName="framework-agreement">fa-wo-rc</cbc:ContractingSystemTypeCode>
         </cac:ContractingSystem>
         <cac:ContractingSystem>
            <cbc:ContractingSystemTypeCode listName="dps-usage">none</cbc:ContractingSystemTypeCode>
         </cac:ContractingSystem>
      </cac:TenderingProcess>
      <cac:ProcurementProject>
         <cbc:ID>LOT 4</cbc:ID>
         <cbc:Name languageID="FRA">Maintenance des équipements de marque RIELLO-GTEC</cbc:Name>
         <cbc:Description languageID="FRA">Maintenance des équipements de marque RIELLO-GTEC</cbc:Description>
         <cbc:ProcurementTypeCode listName="contract-nature">services</cbc:ProcurementTypeCode>
         <cbc:Note languageID="FRA">S'agissant de la maintenance corrective : accord-cadre sans minimum avec un maximum annuel de 15 000 Euros</cbc:Note>
         <cac:MainCommodityClassification>
            <cbc:ItemClassificationCode listName="cpv">50532400</cbc:ItemClassificationCode>
         </cac:MainCommodityClassification>
         <cac:RealizedLocation>
            <cac:Address>
               <cbc:StreetName>Voir inventaire annexé au CCTP et 1.1. règlement de consultation</cbc:StreetName>
               <cbc:CityName>AUNAY-SUR-ODON, CAEN, FALAISE, LISIEUX</cbc:CityName>
               <cbc:PostalZone>14000
14100
14400
14700</cbc:PostalZone>
               <cbc:CountrySubentityCode listName="nuts">FRD11</cbc:CountrySubentityCode>
               <cac:Country>
                  <cbc:IdentificationCode listName="country">FRA</cbc:IdentificationCode>
               </cac:Country>
            </cac:Address>
         </cac:RealizedLocation>
         <cac:PlannedPeriod>
            <cbc:StartDate>2025-11-01+02:00</cbc:StartDate>
            <cbc:EndDate>2026-10-31+02:00</cbc:EndDate>
         </cac:PlannedPeriod>
         <cac:ContractExtension>
            <cbc:MaximumNumberNumeric>3</cbc:MaximumNumberNumeric>
         </cac:ContractExtension>
      </cac:ProcurementProject>
   </cac:ProcurementProjectLot>
   <cac:ProcurementProjectLot>
      <cbc:ID schemeName="Lot">LOT-0006</cbc:ID>
      <cac:TenderingTerms>
         <cbc:VariantConstraintCode listName="permission">not-allowed</cbc:VariantConstraintCode>
         <cbc:FundingProgramCode listName="eu-funded">no-eu-funds</cbc:FundingProgramCode>
         <cac:CallForTendersDocumentReference>
            <cbc:ID>https://www.marches-publics.gouv.fr/?page=Entreprise.EntrepriseAdvancedSearch&amp;AllCons&amp;id=2717768&amp;orgAcronyme=x7c</cbc:ID>
            <cbc:DocumentType>non-restricted-document</cbc:DocumentType>
            <cac:Attachment>
               <cac:ExternalReference>
                  <cbc:URI>https://www.marches-publics.gouv.fr/?page=Entreprise.EntrepriseAdvancedSearch&amp;AllCons&amp;id=2717768&amp;orgAcronyme=x7c</cbc:URI>
               </cac:ExternalReference>
            </cac:Attachment>
         </cac:CallForTendersDocumentReference>
         <cac:TendererQualificationRequest>
            <cac:SpecificTendererRequirement>
               <cbc:TendererRequirementTypeCode listName="selection-criteria-source">epo-procurement-document</cbc:TendererRequirementTypeCode>
            </cac:SpecificTendererRequirement>
         </cac:TendererQualificationRequest>
         <cac:TendererQualificationRequest>
            <cac:SpecificTendererRequirement>
               <cbc:TendererRequirementTypeCode listName="reserved-procurement">none</cbc:TendererRequirementTypeCode>
            </cac:SpecificTendererRequirement>
         </cac:TendererQualificationRequest>
         <cac:ContractExecutionRequirement>
            <cbc:ExecutionRequirementCode listName="conditions">performance</cbc:ExecutionRequirementCode>
         </cac:ContractExecutionRequirement>
         <cac:ContractExecutionRequirement>
            <cbc:ExecutionRequirementCode listName="reserved-execution">no</cbc:ExecutionRequirementCode>
         </cac:ContractExecutionRequirement>
         <cac:ContractExecutionRequirement>
            <cbc:ExecutionRequirementCode listName="einvoicing">required</cbc:ExecutionRequirementCode>
         </cac:ContractExecutionRequirement>
         <cac:ContractExecutionRequirement>
            <cbc:ExecutionRequirementCode listName="ecatalog-submission">allowed</cbc:ExecutionRequirementCode>
         </cac:ContractExecutionRequirement>
         <cac:ContractExecutionRequirement>
            <cbc:ExecutionRequirementCode listName="esignature-submission">true</cbc:ExecutionRequirementCode>
         </cac:ContractExecutionRequirement>
         <cac:AwardingTerms>
            <cac:AwardingCriterion>
               <cac:SubordinateAwardingCriterion>
                  <ext:UBLExtensions>
                     <ext:UBLExtension>
                        <ext:ExtensionContent>
                           <efext:EformsExtension>
                              <efac:AwardCriterionParameter>
                                 <efbc:ParameterCode listName="number-weight">per-exa</efbc:ParameterCode>
                                 <efbc:ParameterNumeric>50</efbc:ParameterNumeric>
                              </efac:AwardCriterionParameter>
                           </efext:EformsExtension>
                        </ext:ExtensionContent>
                     </ext:UBLExtension>
                  </ext:UBLExtensions>
                  <cbc:AwardingCriterionTypeCode listName="award-criterion-type">quality</cbc:AwardingCriterionTypeCode>
                  <cbc:Description languageID="FRA">Valeur technique :
- modalités d'organisation des maintenances et mode opératoire: 20 %
- pertinence des moyens humains dédiés à la prestation : 15 % 
- moyens techniques mis à dispositions : 10 % 
-  démarches de sécurité mises en oeuvre : 5 %  
</cbc:Description>
               </cac:SubordinateAwardingCriterion>
               <cac:SubordinateAwardingCriterion>
                  <ext:UBLExtensions>
                     <ext:UBLExtension>
                        <ext:ExtensionContent>
                           <efext:EformsExtension>
                              <efac:AwardCriterionParameter>
                                 <efbc:ParameterCode listName="number-weight">per-exa</efbc:ParameterCode>
                                 <efbc:ParameterNumeric>45</efbc:ParameterNumeric>
                              </efac:AwardCriterionParameter>
                           </efext:EformsExtension>
                        </ext:ExtensionContent>
                     </ext:UBLExtension>
                  </ext:UBLExtensions>
                  <cbc:AwardingCriterionTypeCode listName="award-criterion-type">price</cbc:AwardingCriterionTypeCode>
                  <cbc:Description languageID="FRA">Prix</cbc:Description>
               </cac:SubordinateAwardingCriterion>
               <cac:SubordinateAwardingCriterion>
                  <ext:UBLExtensions>
                     <ext:UBLExtension>
                        <ext:ExtensionContent>
                           <efext:EformsExtension>
                              <efac:AwardCriterionParameter>
                                 <efbc:ParameterCode listName="number-weight">per-exa</efbc:ParameterCode>
                                 <efbc:ParameterNumeric>5</efbc:ParameterNumeric>
                              </efac:AwardCriterionParameter>
                           </efext:EformsExtension>
                        </ext:ExtensionContent>
                     </ext:UBLExtension>
                  </ext:UBLExtensions>
                  <cbc:AwardingCriterionTypeCode listName="award-criterion-type">quality</cbc:AwardingCriterionTypeCode>
                  <cbc:Description languageID="FRA">Démarches environnementales : gestion des déchets : recyclage et traitement des équipements obsolètes et des déchets électroniques</cbc:Description>
               </cac:SubordinateAwardingCriterion>
            </cac:AwardingCriterion>
         </cac:AwardingTerms>
         <cac:AdditionalInformationParty>
            <cac:PartyIdentification>
               <cbc:ID>ORG-0001</cbc:ID>
            </cac:PartyIdentification>
         </cac:AdditionalInformationParty>
         <cac:DocumentProviderParty>
            <cac:PartyIdentification>
               <cbc:ID>ORG-0001</cbc:ID>
            </cac:PartyIdentification>
         </cac:DocumentProviderParty>
         <cac:TenderRecipientParty>
            <cbc:EndpointID>https://www.marches-publics.gouv.fr/?page=Entreprise.EntrepriseAdvancedSearch&amp;AllCons&amp;id=2717768&amp;orgAcronyme=x7c</cbc:EndpointID>
         </cac:TenderRecipientParty>
         <cac:TenderEvaluationParty>
            <cac:PartyIdentification>
               <cbc:ID>ORG-0001</cbc:ID>
            </cac:PartyIdentification>
         </cac:TenderEvaluationParty>
         <cac:TenderValidityPeriod>
            <cbc:DurationMeasure unitCode="DAY">90</cbc:DurationMeasure>
         </cac:TenderValidityPeriod>
         <cac:AppealTerms>
            <cac:AppealInformationParty>
               <cac:PartyIdentification>
                  <cbc:ID>ORG-0002</cbc:ID>
               </cac:PartyIdentification>
            </cac:AppealInformationParty>
            <cac:AppealReceiverParty>
               <cac:PartyIdentification>
                  <cbc:ID>ORG-0002</cbc:ID>
               </cac:PartyIdentification>
            </cac:AppealReceiverParty>
            <cac:MediationParty>
               <cac:PartyIdentification>
                  <cbc:ID>ORG-0003</cbc:ID>
               </cac:PartyIdentification>
            </cac:MediationParty>
         </cac:AppealTerms>
         <cac:Language>
            <cbc:ID>FRA</cbc:ID>
         </cac:Language>
         <cac:PostAwardProcess>
            <cbc:ElectronicOrderUsageIndicator>false</cbc:ElectronicOrderUsageIndicator>
            <cbc:ElectronicPaymentUsageIndicator>true</cbc:ElectronicPaymentUsageIndicator>
         </cac:PostAwardProcess>
      </cac:TenderingTerms>
      <cac:TenderingProcess>
         <cbc:SubmissionMethodCode listName="esubmission">required</cbc:SubmissionMethodCode>
         <cbc:GovernmentAgreementConstraintIndicator>true</cbc:GovernmentAgreementConstraintIndicator>
         <cac:TenderSubmissionDeadlinePeriod>
            <cbc:EndDate>2025-08-18+02:00</cbc:EndDate>
            <cbc:EndTime>12:00:00+02:00</cbc:EndTime>
         </cac:TenderSubmissionDeadlinePeriod>
         <cac:AuctionTerms>
            <cbc:AuctionConstraintIndicator>false</cbc:AuctionConstraintIndicator>
         </cac:AuctionTerms>
         <cac:FrameworkAgreement>
            <cbc:MaximumOperatorQuantity>0</cbc:MaximumOperatorQuantity>
            <cac:SubsequentProcessTenderRequirement>
               <cbc:Name>buyer-categories</cbc:Name>
            </cac:SubsequentProcessTenderRequirement>
         </cac:FrameworkAgreement>
         <cac:ContractingSystem>
            <cbc:ContractingSystemTypeCode listName="framework-agreement">fa-wo-rc</cbc:ContractingSystemTypeCode>
         </cac:ContractingSystem>
         <cac:ContractingSystem>
            <cbc:ContractingSystemTypeCode listName="dps-usage">none</cbc:ContractingSystemTypeCode>
         </cac:ContractingSystem>
      </cac:TenderingProcess>
      <cac:ProcurementProject>
         <cbc:ID>LOT 5</cbc:ID>
         <cbc:Name languageID="FRA">Maintenance des équipements de marque S2S LEGRAND</cbc:Name>
         <cbc:Description languageID="FRA">Maintenance des équipements de marque S2S LEGRAND</cbc:Description>
         <cbc:ProcurementTypeCode listName="contract-nature">services</cbc:ProcurementTypeCode>
         <cbc:Note languageID="FRA">S'agissant de la maintenance corrective : accord-cadre sans minimum avec un maximum annuel de 10 000 Euros</cbc:Note>
         <cac:MainCommodityClassification>
            <cbc:ItemClassificationCode listName="cpv">50532400</cbc:ItemClassificationCode>
         </cac:MainCommodityClassification>
         <cac:RealizedLocation>
            <cac:Address>
               <cbc:StreetName>Voir inventaire annexé au CCTP et 1.1. règlement de consultation</cbc:StreetName>
               <cbc:CityName>BAYEUX, CAEN, PONT L'EVEQUE</cbc:CityName>
               <cbc:PostalZone>14000
14100
14400</cbc:PostalZone>
               <cbc:CountrySubentityCode listName="nuts">FRD11</cbc:CountrySubentityCode>
               <cac:Country>
                  <cbc:IdentificationCode listName="country">FRA</cbc:IdentificationCode>
               </cac:Country>
            </cac:Address>
         </cac:RealizedLocation>
         <cac:PlannedPeriod>
            <cbc:StartDate>2025-11-01+02:00</cbc:StartDate>
            <cbc:EndDate>2026-10-31+02:00</cbc:EndDate>
         </cac:PlannedPeriod>
         <cac:ContractExtension>
            <cbc:MaximumNumberNumeric>3</cbc:MaximumNumberNumeric>
         </cac:ContractExtension>
      </cac:ProcurementProject>
   </cac:ProcurementProjectLot>
</ContractNotice>