<?xml version="1.0" encoding="UTF-8" standalone="no"?><ContractNotice xmlns="urn:oasis:names:specification:ubl:schema:xsd:ContractNotice-2" xmlns:cac="urn:oasis:names:specification:ubl:schema:xsd:CommonAggregateComponents-2" xmlns:cbc="urn:oasis:names:specification:ubl:schema:xsd:CommonBasicComponents-2" xmlns:efac="http://data.europa.eu/p27/eforms-ubl-extension-aggregate-components/1" xmlns:efbc="http://data.europa.eu/p27/eforms-ubl-extension-basic-components/1" xmlns:efext="http://data.europa.eu/p27/eforms-ubl-extensions/1" xmlns:ext="urn:oasis:names:specification:ubl:schema:xsd:CommonExtensionComponents-2">
   <ext:UBLExtensions>
      <ext:UBLExtension>
         <ext:ExtensionContent>
            <efext:EformsExtension>
               <efac:Changes>
                  <efbc:ChangedNoticeIdentifier>309243-2025</efbc:ChangedNoticeIdentifier>
                  <efac:ChangeReason>
                     <cbc:ReasonCode listName="change-corrig-justification">cor-buy</cbc:ReasonCode>
                     <efbc:ReasonDescription languageID="ELL">Σύμφωνα με το συμπλήρωμα</efbc:ReasonDescription>
                  </efac:ChangeReason>
               </efac:Changes>
               <efac:NoticeSubType>
                  <cbc:SubTypeCode listName="notice-subtype">17</cbc:SubTypeCode>
               </efac:NoticeSubType>
               <efac:Organizations>
                  <efac:Organization>
                     <efac:Company>
                        <cbc:WebsiteURI>www.admie.gr</cbc:WebsiteURI>
                        <cac:PartyIdentification>
                           <cbc:ID schemeName="organization">ORG-0001</cbc:ID>
                        </cac:PartyIdentification>
                        <cac:PartyName>
                           <cbc:Name languageID="ELL">ΑΝΕΞΑΡΤΗΤΟΣ ΔΙΑΧΕΙΡΙΣΤΗΣ ΜΕΤΑΦΟΡΑΣ ΗΛΕΚΤΡΙΚΗΣ ΕΝΕΡΓΕΙΑΣ Α.Ε. (ΑΔΜΗΕ Α.Ε.)</cbc:Name>
                        </cac:PartyName>
                        <cac:PostalAddress>
                           <cbc:StreetName>ΔΥΡΡΑΧΙΟΥ 89</cbc:StreetName>
                           <cbc:AdditionalStreetName>Ι. Ανδριοπούλου</cbc:AdditionalStreetName>
                           <cbc:Department>Ι. Ανδριοπούλου</cbc:Department>
                           <cbc:CityName>ΑΘΗΝΑ</cbc:CityName>
                           <cbc:PostalZone>104 43</cbc:PostalZone>
                           <cbc:CountrySubentityCode listName="nuts">EL303</cbc:CountrySubentityCode>
                           <cac:Country>
                              <cbc:IdentificationCode listName="country">GRC</cbc:IdentificationCode>
                           </cac:Country>
                        </cac:PostalAddress>
                        <cac:PartyLegalEntity>
                           <cbc:CompanyID>1031.F01175.0001</cbc:CompanyID>
                        </cac:PartyLegalEntity>
                        <cac:Contact>
                           <cbc:Name>Ι. Ανδριοπούλου</cbc:Name>
                           <cbc:Telephone>+30 210 519 2607</cbc:Telephone>
                           <cbc:ElectronicMail>i.andriopoulou@admie.gr</cbc:ElectronicMail>
                        </cac:Contact>
                     </efac:Company>
                  </efac:Organization>
                  <efac:Organization>
                     <efac:Company>
                        <cbc:WebsiteURI>https://www.aepp-procurement.gr/</cbc:WebsiteURI>
                        <cac:PartyIdentification>
                           <cbc:ID schemeName="organization">ORG-0002</cbc:ID>
                        </cac:PartyIdentification>
                        <cac:PartyName>
                           <cbc:Name languageID="ELL">ΕΝΙΑΙΑ ΑΡΧΗ ΔΗΜΟΣΙΩΝ ΣΥΜΒΑΣΕΩΝ</cbc:Name>
                        </cac:PartyName>
                        <cac:PostalAddress>
                           <cbc:StreetName>ΔΩΡΟΥ 7-9</cbc:StreetName>
                           <cbc:CityName>ΑΘΗΝΑ</cbc:CityName>
                           <cbc:PostalZone>104 32</cbc:PostalZone>
                           <cbc:CountrySubentityCode listName="nuts">EL303</cbc:CountrySubentityCode>
                           <cac:Country>
                              <cbc:IdentificationCode listName="country">GRC</cbc:IdentificationCode>
                           </cac:Country>
                        </cac:PostalAddress>
                        <cac:PartyLegalEntity>
                           <cbc:CompanyID>1000.E00961.0001</cbc:CompanyID>
                        </cac:PartyLegalEntity>
                        <cac:Contact>
                           <cbc:Telephone>+302132141227</cbc:Telephone>
                           <cbc:ElectronicMail>grafeioproedrou@aepp-procurement.gr</cbc:ElectronicMail>
                        </cac:Contact>
                     </efac:Company>
                  </efac:Organization>
                  <efac:Organization>
                     <efac:Company>
                        <cbc:WebsiteURI>https://op.europa.eu</cbc:WebsiteURI>
                        <cac:PartyIdentification>
                           <cbc:ID schemeName="organization">ORG-0000</cbc:ID>
                        </cac:PartyIdentification>
                        <cac:PartyName>
                           <cbc:Name languageID="ELL">Publications Office of the European Union</cbc:Name>
                        </cac:PartyName>
                        <cac:PostalAddress>
                           <cbc:CityName>Luxembourg</cbc:CityName>
                           <cbc:PostalZone>2417</cbc:PostalZone>
                           <cbc:CountrySubentityCode listName="nuts">LU000</cbc:CountrySubentityCode>
                           <cac:Country>
                              <cbc:IdentificationCode listName="country">LUX</cbc:IdentificationCode>
                           </cac:Country>
                        </cac:PostalAddress>
                        <cac:PartyLegalEntity>
                           <cbc:CompanyID>PUBL</cbc:CompanyID>
                        </cac:PartyLegalEntity>
                        <cac:Contact>
                           <cbc:Telephone>+352 29291</cbc:Telephone>
                           <cbc:ElectronicMail>ted@publications.europa.eu</cbc:ElectronicMail>
                        </cac:Contact>
                     </efac:Company>
                  </efac:Organization>
               </efac:Organizations>
            <efac:Publication><efbc:NoticePublicationID schemeName="ojs-notice-id">00365563-2025</efbc:NoticePublicationID><efbc:GazetteID schemeName="ojs-id">108/2025</efbc:GazetteID><efbc:PublicationDate>2025-06-06+02:00</efbc:PublicationDate></efac:Publication></efext:EformsExtension>
         </ext:ExtensionContent>
      </ext:UBLExtension>
   </ext:UBLExtensions>
   <cbc:UBLVersionID>2.3</cbc:UBLVersionID>
   <cbc:CustomizationID>eforms-sdk-1.13</cbc:CustomizationID>
   <cbc:ID schemeName="notice-id">1ec9c586-4476-447b-8c4b-771c3ad9144b</cbc:ID>
   <cbc:ContractFolderID>7a62d9f7-9d51-499b-84fd-720355ddd7ca</cbc:ContractFolderID>
   <cbc:IssueDate>2025-06-05Z</cbc:IssueDate>
   <cbc:IssueTime>11:27:53Z</cbc:IssueTime>
   <cbc:VersionID>01</cbc:VersionID>
   <cbc:RegulatoryDomain>32014L0025</cbc:RegulatoryDomain>
   <cbc:NoticeTypeCode listName="competition">cn-standard</cbc:NoticeTypeCode>
   <cbc:NoticeLanguageCode listName="language">ELL</cbc:NoticeLanguageCode>
   <cac:ContractingParty>
      <cbc:BuyerProfileURI>https://www.admie.gr</cbc:BuyerProfileURI>
      <cac:ContractingPartyType>
         <cbc:PartyTypeCode listName="buyer-legal-type">pub-undert-cga</cbc:PartyTypeCode>
      </cac:ContractingPartyType>
      <cac:ContractingActivity>
         <cbc:ActivityTypeCode listName="entity-activity">electricity</cbc:ActivityTypeCode>
      </cac:ContractingActivity>
      <cac:Party>
         <cac:PartyIdentification>
            <cbc:ID schemeName="organization">ORG-0001</cbc:ID>
         </cac:PartyIdentification>
         <cac:ServiceProviderParty>
            <cbc:ServiceTypeCode listName="organisation-role">ted-esen</cbc:ServiceTypeCode>
            <cac:Party>
               <cac:PartyIdentification>
                  <cbc:ID schemeName="organization">ORG-0000</cbc:ID>
               </cac:PartyIdentification>
            </cac:Party>
         </cac:ServiceProviderParty>
      </cac:Party>
   </cac:ContractingParty>
   <cac:TenderingTerms>
      <cac:TendererQualificationRequest>
         <cac:SpecificTendererRequirement>
            <cbc:TendererRequirementTypeCode listName="exclusion-grounds-source">epo-sub-espd</cbc:TendererRequirementTypeCode>
         </cac:SpecificTendererRequirement>
      </cac:TendererQualificationRequest>
   </cac:TenderingTerms>
   <cac:TenderingProcess>
      <cbc:ProcedureCode listName="procurement-procedure-type">open</cbc:ProcedureCode>
      <cac:ProcessJustification>
         <cbc:ProcessReasonCode listName="accelerated-procedure">false</cbc:ProcessReasonCode>
      </cac:ProcessJustification>
   </cac:TenderingProcess>
   <cac:ProcurementProject>
      <cbc:Name languageID="ELL">ΔΕΑ 402425 ΠΡΟΜΗΘΕΙΑ ΕΙΔΩΝ ΙΜΑΤΙΣΜΟΥ, ΥΠΟΔΗΣΗΣ &amp; ΜΕΣΩΝ ΑΤΟΜΙΚΗΣ ΠΡΟΣΤΑΣΙΑΣ</cbc:Name>
      <cbc:Description languageID="ELL">ΔΕΑ 402425 ΠΡΟΜΗΘΕΙΑ ΕΙΔΩΝ ΙΜΑΤΙΣΜΟΥ, ΥΠΟΔΗΣΗΣ &amp; ΜΕΣΩΝ ΑΤΟΜΙΚΗΣ ΠΡΟΣΤΑΣΙΑΣ</cbc:Description>
      <cbc:ProcurementTypeCode listName="contract-nature">supplies</cbc:ProcurementTypeCode>
      <cac:MainCommodityClassification>
         <cbc:ItemClassificationCode listName="cpv">18300000</cbc:ItemClassificationCode>
      </cac:MainCommodityClassification>
      <cac:AdditionalCommodityClassification>
         <cbc:ItemClassificationCode listName="cpv">35100000</cbc:ItemClassificationCode>
      </cac:AdditionalCommodityClassification>
      <cac:AdditionalCommodityClassification>
         <cbc:ItemClassificationCode listName="cpv">18800000</cbc:ItemClassificationCode>
      </cac:AdditionalCommodityClassification>
      <cac:RealizedLocation>
         <cac:Address>
            <cbc:CityName>ΑΘΗΝΑ</cbc:CityName>
            <cbc:CountrySubentityCode listName="nuts">EL303</cbc:CountrySubentityCode>
            <cac:Country>
               <cbc:IdentificationCode listName="country">GRC</cbc:IdentificationCode>
            </cac:Country>
         </cac:Address>
      </cac:RealizedLocation>
   </cac:ProcurementProject>
   <cac:ProcurementProjectLot>
      <cbc:ID schemeName="Lot">LOT-0001</cbc:ID>
      <cac:TenderingTerms>
         <cbc:FundingProgramCode listName="eu-funded">no-eu-funds</cbc:FundingProgramCode>
         <cbc:RecurringProcurementIndicator>false</cbc:RecurringProcurementIndicator>
         <cac:RequiredFinancialGuarantee>
            <cbc:GuaranteeTypeCode listName="tender-guarantee-required">true</cbc:GuaranteeTypeCode>
            <cbc:Description languageID="ELL"> Κάθε Οικονομικός Φορέας για τη συμμετοχή του για το σύνολο των ειδών
του διαγωνισμού (υλικά, ανταλλακτικά και υπηρεσίες) καταθέτει Εγγυητική Επιστολή Συμμετοχής, σύμφωνα με το
υπόδειγμα της Εταιρείας, ποσού το οποίο αντιστοιχεί στο 2 της εκτιμώμενης αξίας του προσφερόμενου τμήμταος για το/τα οποία συμμετέχει</cbc:Description>
         </cac:RequiredFinancialGuarantee>
         <cac:CallForTendersDocumentReference>
            <cbc:ID>ΔΕΑ 402425</cbc:ID>
            <cbc:DocumentType>non-restricted-document</cbc:DocumentType>
            <cac:Attachment>
               <cac:ExternalReference>
                  <cbc:URI>www.marketsite.gr</cbc:URI>
               </cac:ExternalReference>
            </cac:Attachment>
         </cac:CallForTendersDocumentReference>
         <cac:PaymentTerms>
            <cbc:Note languageID="ELL">Ίδιοι πόροι</cbc:Note>
         </cac:PaymentTerms>
         <cac:TendererQualificationRequest>
            <cac:SpecificTendererRequirement>
               <cbc:TendererRequirementTypeCode listName="selection-criteria-source">epo-sub-espd</cbc:TendererRequirementTypeCode>
            </cac:SpecificTendererRequirement>
         </cac:TendererQualificationRequest>
         <cac:TendererQualificationRequest>
            <cbc:CompanyLegalFormCode listName="required">false</cbc:CompanyLegalFormCode>
         </cac:TendererQualificationRequest>
         <cac:TendererQualificationRequest>
            <cac:SpecificTendererRequirement>
               <cbc:TendererRequirementTypeCode listName="reserved-procurement">none</cbc:TendererRequirementTypeCode>
            </cac:SpecificTendererRequirement>
         </cac:TendererQualificationRequest>
         <cac:ContractExecutionRequirement>
            <cbc:ExecutionRequirementCode listName="reserved-execution">no</cbc:ExecutionRequirementCode>
         </cac:ContractExecutionRequirement>
         <cac:ContractExecutionRequirement>
            <cbc:ExecutionRequirementCode listName="conditions">performance</cbc:ExecutionRequirementCode>
            <cbc:Description languageID="ELL">.</cbc:Description>
         </cac:ContractExecutionRequirement>
         <cac:ContractExecutionRequirement>
            <cbc:ExecutionRequirementCode listName="einvoicing">not-allowed</cbc:ExecutionRequirementCode>
         </cac:ContractExecutionRequirement>
         <cac:ContractExecutionRequirement>
            <cbc:ExecutionRequirementCode listName="ecatalog-submission">not-allowed</cbc:ExecutionRequirementCode>
         </cac:ContractExecutionRequirement>
         <cac:AdditionalInformationParty>
            <cac:PartyIdentification>
               <cbc:ID>ORG-0001</cbc:ID>
            </cac:PartyIdentification>
         </cac:AdditionalInformationParty>
         <cac:TenderRecipientParty>
            <cbc:EndpointID>www.marketsite.gr</cbc:EndpointID>
         </cac:TenderRecipientParty>
         <cac:TenderValidityPeriod>
            <cbc:DurationMeasure unitCode="DAY">120</cbc:DurationMeasure>
         </cac:TenderValidityPeriod>
         <cac:AppealTerms>
            <cac:PresentationPeriod>
               <cbc:Description languageID="ELL">2.	Σε περίπτωση προσφυγής κατά πράξης της Εταιρείας, η προθεσμία για την άσκηση της προδικαστικής προσφυγής είναι:
(α) 	δέκα (10) ημέρες από την κοινοποίηση της προσβαλλόμενης πράξης στον ενδιαφερόμενο Οικονομικό Φορέα αν η πράξη κοινοποιήθηκε με ηλεκτρονικά μέσα ή τηλεομοιοτυπία ή 
(β) 	δεκαπέντε (15) ημέρες από την κοινοποίηση της προσβαλλόμενης πράξης σε αυτόν αν χρησιμοποιήθηκαν άλλα μέσα επικοινωνίας, άλλως 
(γ) 	δέκα (10) ημέρες από την πλήρη, πραγματική ή τεκμαιρόμενη, γνώση της πράξης που βλάπτει τα συμφέροντα του ενδιαφερόμενου Οικονομικού Φορέα. 
(δ) 	σε περίπτωση παράλειψης, η προθεσμία για την άσκηση της προδικαστικής προσφυγής είναι δεκαπέντε (15) ημέρες από την επομένη της συντέλεσης της προσβαλλόμενης παράλειψης.
</cbc:Description>
            </cac:PresentationPeriod>
            <cac:AppealReceiverParty>
               <cac:PartyIdentification>
                  <cbc:ID>ORG-0002</cbc:ID>
               </cac:PartyIdentification>
            </cac:AppealReceiverParty>
         </cac:AppealTerms>
         <cac:Language>
            <cbc:ID>ELL</cbc:ID>
         </cac:Language>
      </cac:TenderingTerms>
      <cac:TenderingProcess>
         <cbc:SubmissionMethodCode listName="esubmission">required</cbc:SubmissionMethodCode>
         <cbc:GovernmentAgreementConstraintIndicator>true</cbc:GovernmentAgreementConstraintIndicator>
         <cac:TenderSubmissionDeadlinePeriod>
            <cbc:EndDate>2025-04-28+03:00</cbc:EndDate>
            <cbc:EndTime>14:00:00+03:00</cbc:EndTime>
         </cac:TenderSubmissionDeadlinePeriod>
         <cac:OpenTenderEvent>
            <cbc:OccurrenceDate>2025-04-28+03:00</cbc:OccurrenceDate>
            <cbc:OccurrenceTime>15:00:00+03:00</cbc:OccurrenceTime>
         </cac:OpenTenderEvent>
         <cac:AuctionTerms>
            <cbc:AuctionConstraintIndicator>false</cbc:AuctionConstraintIndicator>
         </cac:AuctionTerms>
         <cac:ContractingSystem>
            <cbc:ContractingSystemTypeCode listName="framework-agreement">fa-wo-rc</cbc:ContractingSystemTypeCode>
         </cac:ContractingSystem>
         <cac:ContractingSystem>
            <cbc:ContractingSystemTypeCode listName="dps-usage">none</cbc:ContractingSystemTypeCode>
         </cac:ContractingSystem>
      </cac:TenderingProcess>
      <cac:ProcurementProject>
         <cbc:Name languageID="ELL">ΔΕΑ 402425 ΠΡΟΜΗΘΕΙΑ ΕΙΔΩΝ ΙΜΑΤΙΣΜΟΥ, ΥΠΟΔΗΣΗΣ ΚΑΙ ΜΕΣΩΝ ΑΤΟΜΙΚΗΣ ΠΡΟΣΤΑΣΙΑΣ</cbc:Name>
         <cbc:Description languageID="ELL">ΔΕΑ 402425 ΠΡΟΜΗΘΕΙΑ ΕΙΔΩΝ ΙΜΑΤΙΣΜΟΥ, ΥΠΟΔΗΣΗΣ ΚΑΙ ΜΕΣΩΝ ΑΤΟΜΙΚΗΣ ΠΡΟΣΤΑΣΙΑΣ</cbc:Description>
         <cbc:ProcurementTypeCode listName="contract-nature">supplies</cbc:ProcurementTypeCode>
         <cac:RequestedTenderTotal>
            <cbc:EstimatedOverallContractAmount currencyID="EUR">10279406</cbc:EstimatedOverallContractAmount>
         </cac:RequestedTenderTotal>
         <cac:MainCommodityClassification>
            <cbc:ItemClassificationCode listName="cpv">18300000</cbc:ItemClassificationCode>
         </cac:MainCommodityClassification>
         <cac:AdditionalCommodityClassification>
            <cbc:ItemClassificationCode listName="cpv">18800000</cbc:ItemClassificationCode>
         </cac:AdditionalCommodityClassification>
         <cac:AdditionalCommodityClassification>
            <cbc:ItemClassificationCode listName="cpv">35100000</cbc:ItemClassificationCode>
         </cac:AdditionalCommodityClassification>
         <cac:RealizedLocation>
            <cac:Address>
               <cbc:CountrySubentityCode listName="nuts">EL303</cbc:CountrySubentityCode>
               <cac:Country>
                  <cbc:IdentificationCode listName="country">GRC</cbc:IdentificationCode>
               </cac:Country>
            </cac:Address>
         </cac:RealizedLocation>
         <cac:PlannedPeriod>
            <cbc:DurationMeasure unitCode="YEAR">4</cbc:DurationMeasure>
         </cac:PlannedPeriod>
         <cac:ContractExtension>
            <cbc:MaximumNumberNumeric>1</cbc:MaximumNumberNumeric>
         </cac:ContractExtension>
      </cac:ProcurementProject>
   </cac:ProcurementProjectLot>
</ContractNotice>